stable_delusion/__init__.py
stable_delusion/builders.py
stable_delusion/client/__init__.py
stable_delusion/client/gemini_client.py
stable_delusion/config/__init__.py
stable_delusion/config/config.py
stable_delusion/config/config_manager.py
stable_delusion/config/constants.py
stable_delusion/exceptions/__init__.py
stable_delusion/exceptions/api_error.py
stable_delusion/exceptions/authentication_error.py
stable_delusion/exceptions/configuration_error.py
stable_delusion/exceptions/file_operation_error.py
stable_delusion/exceptions/image_generation_error.py
stable_delusion/exceptions/nano_api_error.py
stable_delusion/exceptions/upscaling_error.py
stable_delusion/exceptions/validation_error.py
stable_delusion/generate/__init__.py
stable_delusion/generate/generation_config.py
stable_delusion/hallucinate.py
stable_delusion/main.py
stable_delusion/models/__init__.py
stable_delusion/models/client_config/__init__.py
stable_delusion/models/client_config/app_config.py
stable_delusion/models/client_config/aws_config.py
stable_delusion/models/client_config/gcp_config.py
stable_delusion/models/client_config/gemini_client_config.py
stable_delusion/models/client_config/image_generation_config.py
stable_delusion/models/client_config/seedream_config.py
stable_delusion/models/client_config/storage_config.py
stable_delusion/models/metadata.py
stable_delusion/models/requests/__init__.py
stable_delusion/models/requests/generate_image_request.py
stable_delusion/models/requests/upscale_image_request.py
stable_delusion/models/requests/validation.py
stable_delusion/models/responses/__init__.py
stable_delusion/models/responses/api_info_response.py
stable_delusion/models/responses/base_response.py
stable_delusion/models/responses/error_response.py
stable_delusion/models/responses/generate_image_response.py
stable_delusion/models/responses/health_response.py
stable_delusion/models/responses/upscale_image_response.py
stable_delusion/models/token_usage.py
stable_delusion-0.1.5.dist-info/METADATA
stable_delusion-0.1.5.dist-info/WHEEL
stable_delusion-0.1.5.dist-info/entry_points.txt
stable_delusion-0.1.5.dist-info/RECORD
