Metadata-Version: 2.4
Name: stable-delusion
Version: 0.1.5
Summary: Helps you hallucinate by providing an interface for AI generation models (Nano Banana, Seedream 4.0)
License: MIT
Keywords: ai,image-generation,gemini,seedream,cli,api
Author: Lene Preuss
Author-email: lene.preuss@gmail.com
Requires-Python: >=3.10,<4.0
Classifier: Development Status :: 3 - Alpha
Classifier: Intended Audience :: Developers
Classifier: License :: OSI Approved :: MIT License
Classifier: Operating System :: OS Independent
Classifier: Programming Language :: Python :: 3
Classifier: Programming Language :: Python :: 3.10
Classifier: Programming Language :: Python :: 3.11
Classifier: Programming Language :: Python :: 3.12
Classifier: Programming Language :: Python :: 3.13
Classifier: Programming Language :: Python :: 3.14
Classifier: Topic :: Multimedia :: Graphics
Classifier: Topic :: Scientific/Engineering :: Artificial Intelligence
Requires-Dist: boto3 (>=1.40.39,<2.0.0)
Requires-Dist: botocore (>=1.40.39,<2.0.0)
Requires-Dist: byteplus-python-sdk-v2 (>=3.0.12,<4.0.0)
Requires-Dist: coloredlogs (>=15.0.1,<16.0.0)
Requires-Dist: flask (>=3.1.2,<4.0.0)
Requires-Dist: google-cloud-aiplatform (>=1.115.0,<2.0.0)
Requires-Dist: google-genai (>=1.38.0,<2.0.0)
Requires-Dist: pillow (>=11.3.0,<12.0.0)
Requires-Dist: poetry-core (>=2.2.1,<3.0.0)
Requires-Dist: python-dotenv (>=1.1.1,<2.0.0)
Project-URL: Bug Tracker, https://gitlab.com/lilacashes/stable-delusion/-/issues
Project-URL: Changelog, https://gitlab.com/lilacashes/stable-delusion/-/blob/main/CHANGELOG.md
Project-URL: Documentation, https://gitlab.com/lilacashes/stable-delusion/-/blob/main/README.md
Project-URL: Homepage, https://gitlab.com/lilacashes/stable-delusion
Project-URL: Repository, https://gitlab.com/lilacashes/stable-delusion
